{
  "weapon_key": "15409",
  "rarity": 4,
  "display_name": "The Viridescent Hunt",
  "base_stats_json": {
    "baseAtk": 509.605949,
    "subStatKey": "critRate_",
    "subStatValue": 0.27564
  },
  "buffs": {
    "self_modifiers_json": {},
    "self_conditional_modifiers_json": [
      {
        "source": "TheViridescentHunt",
        "conditionKey": "the_viridescent_hunt_cyclone_tick",
        "description": "R5 Verdant Wind: Normal/Charged Attack hits have a 50% chance to generate a Cyclone that deals 80% ATK DMG per tick (every 0.5s for 4s) to drawn-in opponents; can only occur once every 10s.",
        "states": {
          "active": {
            "all_dmgIncFromAtk_": 0.8
          }
        }
      }
    ],
    "team_modifiers_json": {},
    "team_conditional_modifiers_json": []
  }
}
